{"cameraMode":{"drawMode":0,"name":"Shaded","section":"Shading Mode"},"sceneLighting":false,"audioPlay":false,"sceneViewState":{"showFog":true,"showMaterialUpdate":false,"showSkybox":false,"showFlares":true,"showImageEffects":true,"showParticleSystems":true},"in2DMode":false,"pivot":{"x":0.0,"y":-0.24734704196453095,"z":-1.1175870895385743e-8},"rotation":{"x":-0.005378381814807653,"y":0.9898418188095093,"z":-0.1374719738960266,"w":-0.038623351603746417},"size":0.46484068036079409,"orthographic":false}